main.py
mcp_mm_cs_mai-0.1.10.dist-info/METADATA
mcp_mm_cs_mai-0.1.10.dist-info/WHEEL
mcp_mm_cs_mai-0.1.10.dist-info/entry_points.txt
mcp_mm_cs_mai-0.1.10.dist-info/top_level.txt
mcp_mm_cs_mai-0.1.10.dist-info/RECORD
