Metadata-Version: 2.4
Name: mcp-mm-cs-mai
Version: 0.1.10
Summary: Add your description here
Requires-Python: >=3.11
Requires-Dist: firecrawl-py>=2.7.0
Requires-Dist: langchain-community>=0.3.20
Requires-Dist: langchain-openai>=0.3.11
Requires-Dist: lightrag-hku[api]>=1.3.7
Requires-Dist: mcp[cli]>=1.9.1
Requires-Dist: pip>=25.1.1
